Topsis_Khushi_102183044/topsis.py
Topsis_Khushi_102183044-0.0.7.dist-info/LICENSE.txt
Topsis_Khushi_102183044-0.0.7.dist-info/METADATA
Topsis_Khushi_102183044-0.0.7.dist-info/WHEEL
Topsis_Khushi_102183044-0.0.7.dist-info/entry_points.txt
Topsis_Khushi_102183044-0.0.7.dist-info/top_level.txt
Topsis_Khushi_102183044-0.0.7.dist-info/RECORD
