Metadata-Version: 2.1
Name: Topsis-Khushi-102183044
Version: 0.0.7
Summary: Package for calculating topsis score for multiple criteria decision making problems
Home-page: https://github.com/khushipr/TOPSIS
Author: Khushi Prasad
Author-email: khushipr01@gmail.com
License: MIT
Platform: UNKNOWN
Classifier: Programming Language :: Python :: 3
Classifier: License :: OSI Approved :: MIT License
Classifier: Operating System :: OS Independent
License-File: LICENSE.txt
Requires-Dist: pandas
